slack_to_discord/__init__.py
slack_to_discord/__main__.py
slack_to_discord/emojis.py
slack_to_discord/http_stream.py
slack_to_discord/importer.py
slack_to_discord/script.py
slack_to_discord-1.1.7.dist-info/METADATA
slack_to_discord-1.1.7.dist-info/WHEEL
slack_to_discord-1.1.7.dist-info/entry_points.txt
slack_to_discord-1.1.7.dist-info/top_level.txt
slack_to_discord-1.1.7.dist-info/RECORD
