Metadata-Version: 2.1
Name: slack-to-discord
Version: 1.1.7
Summary: Extract data from a Slack export and import it into Discord
Home-page: https://github.com/pR0Ps/slack-to-discord
License: GPLv3
Classifier: Programming Language :: Python :: 3
Classifier: Programming Language :: Python :: 3.8
Classifier: Programming Language :: Python :: 3.9
Classifier: Programming Language :: Python :: 3.10
Classifier: Programming Language :: Python :: 3.11
Classifier: Programming Language :: Python :: 3.12
Classifier: Operating System :: OS Independent
Classifier: Topic :: Communications :: Chat
Classifier: License :: OSI Approved :: GNU General Public License v3 (GPLv3)
Requires-Python: >=3.8.0
Requires-Dist: discord.py <3.0.0,>=2.0.0
Requires-Dist: urllib3 <3.0.0,>=1.26.12
Requires-Dist: iterable-io <2.0.0,>=1.0.0
